bastion_integration/__init__.py
bastion_integration/base_info/__init__.py
bastion_integration/base_info/base_test.py
bastion_integration/base_info/bastion_dto.py
bastion_integration/base_info/custom_error_handler.py
bastion_integration/base_info/fake_dto_info.py
bastion_integration/bastion.py
bastion_integration/bastion_iks/__init__.py
bastion_integration/bastion_iks/async_core.py
bastion_integration/bastion_iks/bastion_iks_dto.py
bastion_integration/bastion_iks/core.py
bastion_integration/bastion_web_socket/__init__.py
bastion_integration/bastion_web_socket/bastion_web_socket_dto.py
bastion_integration/bastion_web_socket/command_info.py
bastion_integration/bastion_web_socket/core.py
bastion_integration/bastion_web_socket/logic.py
bastion_integration/bastion_web_socket/request_types.py
bastion_integration/bastion_web_socket/response_dto.py
bastion_integration-0.2.8.dist-info/LICENSE
bastion_integration-0.2.8.dist-info/METADATA
bastion_integration-0.2.8.dist-info/WHEEL
bastion_integration-0.2.8.dist-info/RECORD
