Metadata-Version: 2.1
Name: bastion_integration
Version: 0.2.8
Summary: Модуль интеграции с Бастион
Author: Mrkorogod
Requires-Python: >=3.10,<4.0
Classifier: Programming Language :: Python :: 3
Classifier: Programming Language :: Python :: 3.10
Classifier: Programming Language :: Python :: 3.11
Classifier: Programming Language :: Python :: 3.12
